{
 "cells": [
  {
   "cell_type": "markdown",
   "metadata": {},
   "source": [
    "Декомпилироваться байд-код питона и изучить его на примере данных вычислений: 1) 4 ** 76 2) 4 ** 77\n",
    "\n",
    "Создать функцию с использованием print и изучить байт-код\n"
   ]
  },
  {
   "cell_type": "code",
   "execution_count": 1,
   "metadata": {},
   "outputs": [
    {
     "name": "stdout",
     "output_type": "stream",
     "text": [
      "  1           0 LOAD_CONST               0 (4)\n",
      "              2 LOAD_CONST               1 (76)\n",
      "              4 BINARY_POWER\n",
      "              6 RETURN_VALUE\n"
     ]
    }
   ],
   "source": [
    "import dis\n",
    "dis.dis('4**76')\n"
   ]
  },
  {
   "cell_type": "code",
   "execution_count": 2,
   "metadata": {},
   "outputs": [
    {
     "name": "stdout",
     "output_type": "stream",
     "text": [
      "  1           0 LOAD_CONST               0 (4)\n",
      "              2 LOAD_CONST               1 (77)\n",
      "              4 BINARY_POWER\n",
      "              6 RETURN_VALUE\n"
     ]
    }
   ],
   "source": [
    "import dis\n",
    "dis.dis('4**77')"
   ]
  },
  {
   "cell_type": "code",
   "execution_count": 5,
   "metadata": {},
   "outputs": [
    {
     "name": "stdout",
     "output_type": "stream",
     "text": [
      "Enter your name \n",
      "Dasha\n",
      "Hello, Dasha\n",
      "  2           0 LOAD_GLOBAL              0 (print)\n",
      "              2 LOAD_CONST               1 ('Enter your name ')\n",
      "              4 CALL_FUNCTION            1\n",
      "              6 POP_TOP\n",
      "\n",
      "  3           8 LOAD_GLOBAL              1 (input)\n",
      "             10 CALL_FUNCTION            0\n",
      "             12 STORE_FAST               0 (a)\n",
      "\n",
      "  4          14 LOAD_GLOBAL              0 (print)\n",
      "             16 LOAD_CONST               2 ('Hello,')\n",
      "             18 LOAD_FAST                0 (a)\n",
      "             20 CALL_FUNCTION            2\n",
      "             22 POP_TOP\n",
      "             24 LOAD_CONST               0 (None)\n",
      "             26 RETURN_VALUE\n"
     ]
    }
   ],
   "source": [
    "def output():\n",
    "    print(\"Enter your name \")\n",
    "    a=input();\n",
    "    print('Hello,', a)\n",
    "output()   \n",
    "dis.dis(output)"
   ]
  },
  {
   "cell_type": "markdown",
   "metadata": {},
   "source": [
    "\n",
    "\n",
    "Посмотреть информацию о модулях. Используя : 1)inspect.ismethod 2)inspect.isroutine 3)inspect.ismodule 4)inspect.getabsfile(inspect)\n"
   ]
  },
  {
   "cell_type": "code",
   "execution_count": 48,
   "metadata": {},
   "outputs": [
    {
     "data": {
      "text/plain": [
       "True"
      ]
     },
     "execution_count": 48,
     "metadata": {},
     "output_type": "execute_result"
    }
   ],
   "source": [
    "import inspect\n",
    "inspect.isroutine(' '.join)\n"
   ]
  },
  {
   "cell_type": "code",
   "execution_count": 49,
   "metadata": {},
   "outputs": [
    {
     "data": {
      "text/plain": [
       "False"
      ]
     },
     "execution_count": 49,
     "metadata": {},
     "output_type": "execute_result"
    }
   ],
   "source": [
    "inspect.ismethod(' '.join)"
   ]
  },
  {
   "cell_type": "code",
   "execution_count": 50,
   "metadata": {},
   "outputs": [
    {
     "data": {
      "text/plain": [
       "True"
      ]
     },
     "execution_count": 50,
     "metadata": {},
     "output_type": "execute_result"
    }
   ],
   "source": [
    "inspect.ismodule(time)"
   ]
  },
  {
   "cell_type": "code",
   "execution_count": 52,
   "metadata": {},
   "outputs": [
    {
     "data": {
      "text/plain": [
       "'c:\\\\users\\\\дарья\\\\appdata\\\\local\\\\programs\\\\python\\\\python37\\\\lib\\\\inspect.py'"
      ]
     },
     "execution_count": 52,
     "metadata": {},
     "output_type": "execute_result"
    }
   ],
   "source": [
    "\n",
    "inspect.getabsfile(inspect)"
   ]
  },
  {
   "cell_type": "code",
   "execution_count": null,
   "metadata": {},
   "outputs": [],
   "source": []
  }
 ],
 "metadata": {
  "kernelspec": {
   "display_name": "Python 3",
   "language": "python",
   "name": "python3"
  },
  "language_info": {
   "codemirror_mode": {
    "name": "ipython",
    "version": 3
   },
   "file_extension": ".py",
   "mimetype": "text/x-python",
   "name": "python",
   "nbconvert_exporter": "python",
   "pygments_lexer": "ipython3",
   "version": "3.7.4"
  }
 },
 "nbformat": 4,
 "nbformat_minor": 4
}
